balderhub/textual/__init__.py
balderhub/textual/_version.py
balderhub/textual/lib/__init__.py
balderhub/textual/lib/scenario_features/__init__.py
balderhub/textual/lib/scenario_features/app_feature.py
balderhub/textual/lib/scenario_features/textual_control_feature.py
balderhub/textual/lib/scenario_features/textual_page.py
balderhub/textual/lib/setup_features/__init__.py
balderhub/textual/lib/utils/__init__.py
balderhub/textual/lib/utils/selector.py
balderhub/textual/lib/utils/components/__init__.py
balderhub/textual/lib/utils/components/textual_element.py
balderhub/textual/lib/utils/components/widgets/__init__.py
balderhub/textual/lib/utils/components/widgets/button.py
balderhub/textual/lib/utils/components/widgets/checkbox.py
balderhub/textual/lib/utils/components/widgets/data_table.py
balderhub/textual/lib/utils/components/widgets/digits.py
balderhub/textual/lib/utils/components/widgets/directory_tree.py
balderhub/textual/lib/utils/components/widgets/footer.py
balderhub/textual/lib/utils/components/widgets/header.py
balderhub/textual/lib/utils/components/widgets/input.py
balderhub/textual/lib/utils/components/widgets/label.py
balderhub/textual/lib/utils/components/widgets/list_item.py
balderhub/textual/lib/utils/components/widgets/loading_indicator.py
balderhub/textual/lib/utils/components/widgets/log.py
balderhub/textual/lib/utils/components/widgets/option_list.py
balderhub/textual/lib/utils/components/widgets/placeholder.py
balderhub/textual/lib/utils/components/widgets/progress_bar.py
balderhub/textual/lib/utils/components/widgets/radio_button.py
balderhub/textual/lib/utils/components/widgets/rule.py
balderhub/textual/lib/utils/components/widgets/select.py
balderhub/textual/lib/utils/components/widgets/static.py
balderhub/textual/lib/utils/components/widgets/switch.py
balderhub/textual/lib/utils/components/widgets/tabs.py
balderhub/textual/lib/utils/components/widgets/text_area.py
balderhub/textual/lib/utils/components/widgets/tree.py
balderhub_textual-0.0.1b0.dist-info/licenses/LICENSE
balderhub_textual-0.0.1b0.dist-info/METADATA
balderhub_textual-0.0.1b0.dist-info/WHEEL
balderhub_textual-0.0.1b0.dist-info/top_level.txt
balderhub_textual-0.0.1b0.dist-info/RECORD
